hadnsone_2/__init__.py
hadnsone_2-0.1.0.dist-info/METADATA
hadnsone_2-0.1.0.dist-info/WHEEL
hadnsone_2-0.1.0.dist-info/RECORD
